{
  "video_path": "E:/train/37_NeedlePassing_demo.mp4",
  "total_frames": 327,
  "fps": 15.0,
  "labels": [
    0,
    1,
    2,
    3,
    4,
    5
  ],
  "annotations": [
    {
      "label": "0",
      "start": 25,
      "end": 57
    },
    {
      "label": "1",
      "start": 58,
      "end": 83
    },
    {
      "label": "2",
      "start": 84,
      "end": 164
    },
    {
      "label": "3",
      "start": 165,
      "end": 182
    },
    {
      "label": "4",
      "start": 183,
      "end": 272
    },
    {
      "label": "5",
      "start": 273,
      "end": 313
    }
  ]
}